<annotation>
	<folder></folder>
	<filename>snap442837333975_png.rf.cd5278674d6d5ba0f169d1a7e956d8fa.jpg</filename>
	<path>snap442837333975_png.rf.cd5278674d6d5ba0f169d1a7e956d8fa.jpg</path>
	<source>
		<database>roboflow.com</database>
	</source>
	<size>
		<width>640</width>
		<height>480</height>
		<depth>3</depth>
	</size>
	<segmented>0</segmented>
	<object>
		<name>red</name>
		<pose>Unspecified</pose>
		<truncated>0</truncated>
		<difficult>0</difficult>
		<occluded>0</occluded>
		<bndbox>
			<xmin>1</xmin>
			<xmax>95</xmax>
			<ymin>419</ymin>
			<ymax>480</ymax>
		</bndbox>
	</object>
</annotation>
